blackcurve/__init__.py
blackcurve/api.py
blackcurve-0.3.1.dist-info/LICENSE
blackcurve-0.3.1.dist-info/METADATA
blackcurve-0.3.1.dist-info/WHEEL
blackcurve-0.3.1.dist-info/top_level.txt
blackcurve-0.3.1.dist-info/RECORD
