Metadata-Version: 2.1
Name: blackcurve
Version: 0.3.1
Summary: An easy to use python interface for BlackCurve's API
Home-page: https://github.com/blackcurve/BlackCurve-API
Author: BlackCurve LTD.
Author-email: george.rowberry@blackcurve.com
License: UNKNOWN
Platform: UNKNOWN
Classifier: Programming Language :: Python
Classifier: License :: OSI Approved :: MIT License
Classifier: Operating System :: OS Independent
Requires-Dist: requests
